{
  "UserNotFound": "Pengguna tidak ditemukan",
  "UserAlreadyExists": "Pengguna dengan email ini sudah ada",
  "UserCreationFailed": "Gagal membuat pengguna",
  "UserUpdateFailed": "Gagal memperbarui pengguna",
  "UserDeletionFailed": "Gagal menghapus pengguna",
  "RoleNotFound": "Peran tidak ditemukan",
  "RoleAlreadyExists": "Peran dengan nama ini sudah ada",
  "RoleCreationFailed": "Gagal membuat peran",
  "RoleUpdateFailed": "Gagal memperbarui peran",
  "RoleDeletionFailed": "Gagal menghapus peran",
  "RoleAssignmentFailed": "Gagal menetapkan peran kepada pengguna",
  "InvalidCredentials": "Email atau kata sandi tidak valid",
  "AccountLocked": "Akun terkunci",
  "AccountDisabled": "Akun dinonaktifkan",
  "TokenExpired": "Token telah kedaluwarsa",
  "TokenInvalid": "Token tidak valid",
  "RefreshTokenExpired": "Token penyegaran telah kedaluwarsa",
  "RefreshTokenRevoked": "Token penyegaran telah dicabut",
  "LoginFailed": "Login gagal",
  "LogoutFailed": "Logout gagal",
  "AccessDenied": "Akses ditolak",
  "InsufficientPermissions": "Izin tidak mencukupi untuk melakukan tindakan ini",
  "UnauthorizedAccess": "Akses tidak diizinkan",
  "ValidationFailed": "Validasi gagal",
  "InternalServerError": "Terjadi kesalahan server internal",
  "BadRequest": "Permintaan tidak valid",
  "NotFound": "Sumber daya tidak ditemukan",
  "Conflict": "Konflik sumber daya",
  "DatabaseError": "Operasi database gagal",
  "CacheError": "Operasi cache gagal"
}